BanglaSpeechRecognition/BanglaSpeechRecognition.py
BanglaSpeechRecognition/__init__.py
BanglaSpeechRecognition-1.0.dist-info/LICENSE.txt
BanglaSpeechRecognition-1.0.dist-info/METADATA
BanglaSpeechRecognition-1.0.dist-info/WHEEL
BanglaSpeechRecognition-1.0.dist-info/top_level.txt
BanglaSpeechRecognition-1.0.dist-info/RECORD
