Metadata-Version: 2.1
Name: BanglaSpeechRecognition
Version: 1.0
Summary: Speech Recognition for Bangla Language developed by Md. Kowsher
Home-page: https://github.com/Kowsher/Bangla-Speech-Recognition.git
Author: Md. Kowsher
Author-email: ga.kowsher@gmail.com
License: MIT
Platform: UNKNOWN
Classifier: Development Status :: 3 - Alpha
Classifier: Intended Audience :: Developers
Classifier: Topic :: Software Development :: Build Tools
Classifier: License :: OSI Approved :: MIT License
Requires-Dist: speechrecognition
